crumbs/__init__.py
crumbs/bpp.py
crumbs/fasta2phylip.py
crumbs/get_failed_simulations_rowids.py
crumbs/get_successful_simulations_rowids.py
crumbs/phylip2arlequin.py
crumbs/retrieve_parameters.py
crumbs/sample.py
crumbs/sequence.py
crumbs/simulate_phylip_sequences.py
crumbs/chelsa/__init__.py
crumbs/chelsa/request.py
crumbs/chelsa/utils.py
crumbs/chelsa/cli/__init__.py
crumbs/chelsa/cli/options.py
crumbs/chelsa/cli/request_cmd.py
crumbs/gbif/__init__.py
crumbs/gbif/request.py
crumbs/gbif/utils.py
crumbs/gbif/cli/__init__.py
crumbs/gbif/cli/options.py
crumbs/gbif/cli/request_cmd.py
crumbs/gis/__init__.py
crumbs/raster/__init__.py
crumbs/raster/animate.py
crumbs/raster/circle_mask.py
crumbs/raster/interpolate.py
crumbs/raster/resample.py
crumbs/raster/rotate_and_rescale.py
crumbs/raster/show_raster.py
crumbs/raster/utils.py
crumbs/sdm/__init__.py
crumbs/sdm/sdm.py
crumbs/sdm/cli/__init__.py
crumbs/sdm/cli/extrapolate_cmd.py
crumbs/sdm/cli/extrapolate_options.py
crumbs/sdm/cli/fit_cmd.py
crumbs/sdm/cli/fit_options.py
quetzal_crumbs-1.0.17.dist-info/LICENSE
quetzal_crumbs-1.0.17.dist-info/METADATA
quetzal_crumbs-1.0.17.dist-info/WHEEL
quetzal_crumbs-1.0.17.dist-info/entry_points.txt
quetzal_crumbs-1.0.17.dist-info/top_level.txt
quetzal_crumbs-1.0.17.dist-info/RECORD
