Metadata-Version: 2.1
Name: quetzal-crumbs
Version: 1.0.17
Summary: General utility scripts for Quetzal projects
Home-page: https://github.com/Becheler/quetzal-CRUMBS
Author: Arnaud Becheler
Author-email: arnaud.becheler@gmail.com
Project-URL: Bug Tracker, https://github.com/Becheler/quetzal-CRUMBS/issues
Classifier: Programming Language :: Python :: 3
Classifier: License :: OSI Approved :: GNU General Public License v3 (GPLv3)
Classifier: Operating System :: OS Independent
Requires-Python: >=3.6
License-File: LICENSE
